{"cameraMode":{"drawMode":0,"name":"Shaded","section":"Shading Mode"},"sceneLighting":true,"audioPlay":false,"sceneViewState":{"showFog":true,"showMaterialUpdate":false,"showSkybox":true,"showFlares":true,"showImageEffects":true,"showParticleSystems":true,"showVisualEffectGraphs":true,"m_FxEnabled":true},"in2DMode":false,"pivot":{"x":504.0522155761719,"y":23.04390525817871,"z":530.6600952148438},"rotation":{"x":0.18434661626815797,"y":0.06432201713323593,"z":-0.01209157332777977,"w":0.980681836605072},"size":10.0,"orthographic":false}